README.txt
setup.cfg
setup.py
imstool/__init__.py
imstool/base.py
imstool/errors.py
imstool/objmanager.py
imstool/register.py
imstool.egg-info/PKG-INFO
imstool.egg-info/SOURCES.txt
imstool.egg-info/dependency_links.txt
imstool.egg-info/entry_points.txt
imstool.egg-info/not-zip-safe
imstool.egg-info/top_level.txt
imstool/bb/__init__.py
imstool/bb/bboard.py
imstool/bb/bbreader.py
imstool/bb/configbb.py
imstool/imscc/__init__.py
imstool/imscc/ccreader.py
imstool/imscc/configcc.py
imstool/imscc/imscc.py
imstool/imscp/__init__.py
imstool/imscp/configcp.py
imstool/imscp/cpreader.py
imstool/imscp/imscp.py
imstool/mitocw/__init__.py
imstool/mitocw/configmit.py
imstool/mitocw/mitocw.py
imstool/mitocw/mitreader.py
imstool/moodle/__init__.py
imstool/moodle/mbreader.py
imstool/moodle/moodle.py
imstool/qti/__init__.py
imstool/qti/qti_1_2.py
imstool/webct/__init__.py
imstool/webct/configwebct.py
imstool/webct/webct.py
imstool/webct/webctreader.py
imstool/webctvista/__init__.py
imstool/webctvista/webctvista.py
imstool/webctvista/webctvistareader.py