Metadata-Version: 1.0
Name: imstool
Version: 0.2
Summary: A python library for reading and writing content packages.
Home-page: UNKNOWN
Author: Brent Lambert
Author-email: brent@enpraxis.net
License: GPLv2
Keywords: IMS,common cartridge,IMSCC,IMSCP,moodle,content package
Platform: UNKNOWN
Classifier: Development Status :: 3 - Alpha
Classifier: Intended Audience :: Developers
Classifier: License :: OSI Approved :: GNU General Public License (GPL)
Classifier: Programming Language :: Python
Classifier: Topic :: Education
Classifier: Topic :: Software Development :: Libraries
